rethon/__init__.py
rethon/base.py
rethon/bitarray_implementation.py
rethon/core.py
rethon/ensemble_generation.py
rethon/numba_re.py
rethon/numpy_implementation.py
rethon/set_implementation.py
rethon/test_rethon.py
rethon/util.py
rethon/config/__init__.py
rethon/config/logging-config.json
rethon/test_data/__init__.py
rethon/test_data/test_data_re_01.json.tar.gz
rethon/test_data/test_data_re_02.json
rethon/test_data/test_data_re_02.json.tar.gz
rethon/test_data/test_data_re_03.json
rethon/test_data/test_data_re_03.json.tar.gz
rethon/test_data/test_data_re_04.json.tar.gz
rethon/test_data/test_data_re_05.json
rethon/test_data/test_data_re_05.json.tar.gz
rethon/test_data/test_data_re_06.json.tar.gz
rethon-1.0.0.dist-info/LICENSE
rethon-1.0.0.dist-info/METADATA
rethon-1.0.0.dist-info/WHEEL
rethon-1.0.0.dist-info/top_level.txt
rethon-1.0.0.dist-info/RECORD
