Metadata-Version: 2.1
Name: rethon
Version: 1.0.0
Summary: A Formal Model of Reflective Equilibrium
Home-page: https://github.com/re-models/rethon
Author: Claus Beisbart, Gregor Betz, Georg Brun, Sebastian Cacean, Andreas Freivogel, Richard Lohse
Author-email: claus.beisbart@philo.unibe.ch, gregor.betz@kit.edu, georg.brun@philo.unibe.ch, sebastian.cacean@kit.edu, andreas.freivogel@philo.unibe.ch, richard.lohse@kit.edu
Classifier: Programming Language :: Python :: 3.8
Classifier: License :: OSI Approved :: MIT License
Classifier: Operating System :: OS Independent
Requires-Python: >=3.8
License-File: LICENSE
Requires-Dist: theodias
